[
  {
    "_key": "admin",
    "_owner": "nobody",
    "_user": "nobody",
    "_version": "4.20.1",
    "acl": {
      "can_change_perms": true,
      "can_share_app": true,
      "can_share_global": true,
      "can_share_user": true,
      "can_write": true,
      "modifiable": true,
      "owner": "admin",
      "perms": {
        "read": [
          "*"
        ],
        "write": [
          "*"
        ]
      },
      "sharing": "app"
    },
    "autoRefresh": 0,
    "collapsedNodes": "",
    "description": "",
    "earliest_time": "-12h",
    "identifying_name": "",
    "isDefault": true,
    "isKpiFilterEnabled": false,
    "isServiceFilterEnabled": false,
    "isTagFilterEnabled": false,
    "kpiFilterString": "",
    "kpiTilesSettings": {
      "isFilterEnabled": false,
      "numTiles": 50
    },
    "kpiWhitelist": [],
    "latest_time": "now",
    "maxDepth": -2,
    "minSeverity": -1,
    "mod_source": "unknown",
    "mod_time": "",
    "mod_timestamp": "2025-07-30T04:27:27.844922+00:00",
    "object_type": "home_view",
    "sandboxId": "all",
    "searchType": "aggregate",
    "serviceFilterString": "",
    "serviceTilesSettings": {
      "isFilterEnabled": false,
      "numTiles": 50
    },
    "serviceWhitelist": "",
    "showDisabledServices": false,
    "showServiceDependencies": false,
    "source_itsi_da": "itsi",
    "tagFilterString": "",
    "tagWhitelist": "",
    "tileSize": "large",
    "title": "",
    "view": "standard",
    "viewType": "tile"
  }
]